py2plpy/__init__.py
py2plpy/command_line.py
py2plpy/plpy.py
py2plpy/py2plpy.py
py2plpy/types.py
py2plpy/tests/__init__.py
py2plpy/tests/fixture.py
py2plpy/tests/test.py
py2plpy-0.4.0.dist-info/LICENSE
py2plpy-0.4.0.dist-info/METADATA
py2plpy-0.4.0.dist-info/WHEEL
py2plpy-0.4.0.dist-info/entry_points.txt
py2plpy-0.4.0.dist-info/top_level.txt
py2plpy-0.4.0.dist-info/RECORD
