Metadata-Version: 2.1
Name: py2plpy
Version: 0.4.0
Summary: Convert python function to PostgreSQL Pl/Python functions
Author-email: Marc Endesfelder <endesfelder.marc@gmail.com>
License: MIT
Classifier: Development Status :: 4 - Beta
Classifier: Programming Language :: Python :: 3
Classifier: License :: OSI Approved :: MIT License
Classifier: Operating System :: OS Independent
Classifier: Intended Audience :: Developers
Classifier: Programming Language :: PL/SQL
Classifier: Topic :: Database :: Database Engines/Servers
Classifier: Topic :: Database
Classifier: Topic :: Software Development :: Code Generators
Requires-Python: >=3.10
License-File: LICENSE
Requires-Dist: typing-extensions ; python_version < "3.12"
